puli/__init__.py
puli/puli.py
puli-0.0.1.dist-info/LICENSE
puli-0.0.1.dist-info/METADATA
puli-0.0.1.dist-info/WHEEL
puli-0.0.1.dist-info/top_level.txt
puli-0.0.1.dist-info/RECORD
