Metadata-Version: 2.1
Name: puli
Version: 0.0.1
Summary: Analyze UVIT L1 data
Home-page: https://github.com/prajwel/puli
Author: Prajwel Joseph
Author-email: prajwel.joseph@gmail.com
License: UNKNOWN
Platform: UNKNOWN
Classifier: Programming Language :: Python :: 3
Classifier: License :: OSI Approved :: Apache Software License
Classifier: Operating System :: OS Independent
Requires-Python: >=3.7
Requires-Dist: numpy
Requires-Dist: astropy
